{
  "flows": [
    {
      "from": "Beschikbaar",
      "to": "Vraag",
      "value": 16.447565123542272,
      "style": {
        "fill": "lightblue"
      }
    },
    {
      "from": "Tekort",
      "to": "Vraag",
      "value": 0.0,
      "style": {
        "fill": "red"
      }
    },
    {
      "from": "Vraag",
      "to": "Beregening",
      "value": 5.424858774690239,
      "style": {
        "fill": "green"
      }
    },
    {
      "from": "Vraag",
      "to": "Peilbeheer",
      "value": 10.522706348852033,
      "style": {
        "fill": "blue"
      }
    },
    {
      "from": "Vraag",
      "to": "Doorspoeling",
      "value": 0.5,
      "style": {
        "fill": "black"
      }
    }
  ]
}