[
  {
    "runID":1,
    "klimaat":"laag",
    "zichtjaar":2023,
    "afvoerverdeling":2018,
    "afvoerbeperking":false,
    "kwa":false,
    "zss":0.0,
    "discharge":"BP18REF2017",
    "demand":"BP18REF2017",
    "demand_corrected":"BP18REF2017_slr0"
  },
  {
    "runID":2,
    "klimaat":"laag",
    "zichtjaar":2050,
    "afvoerverdeling":2018,
    "afvoerbeperking":false,
    "kwa":false,
    "zss":0.3,
    "discharge":"BP18REF2017",
    "demand":"BP18REF2017",
    "demand_corrected":"BP18REF2017_slr0.3"
  },
  {
    "runID":3,
    "klimaat":"laag",
    "zichtjaar":2100,
    "afvoerverdeling":2018,
    "afvoerbeperking":false,
    "kwa":false,
    "zss":0.5,
    "discharge":"BP18REF2017",
    "demand":"BP18REF2017",
    "demand_corrected":"BP18REF2017_slr0.5"
  },
  {
    "runID":4,
    "klimaat":"laag",
    "zichtjaar":2150,
    "afvoerverdeling":2018,
    "afvoerbeperking":false,
    "kwa":false,
    "zss":0.75,
    "discharge":"BP18REF2017",
    "demand":"BP18REF2017",
    "demand_corrected":"BP18REF2017_slr0.75"
  },
  {
    "runID":5,
    "klimaat":"laag",
    "zichtjaar":2200,
    "afvoerverdeling":2018,
    "afvoerbeperking":false,
    "kwa":false,
    "zss":1.0,
    "discharge":"BP18REF2017",
    "demand":"BP18REF2017",
    "demand_corrected":"BP18REF2017_slr1"
  },
  {
    "runID":6,
    "klimaat":"zeer extreem",
    "zichtjaar":2023,
    "afvoerverdeling":2018,
    "afvoerbeperking":false,
    "kwa":false,
    "zss":0.0,
    "discharge":"BP18REF2017",
    "demand":"BP18REF2017",
    "demand_corrected":"BP18REF2017_slr0"
  },
  {
    "runID":7,
    "klimaat":"zeer extreem",
    "zichtjaar":2050,
    "afvoerverdeling":2018,
    "afvoerbeperking":false,
    "kwa":false,
    "zss":0.5,
    "discharge":"BP18STOOM2050",
    "demand":"BP18STOOM2050",
    "demand_corrected":"BP18STOOM2050_slr0.5"
  },
  {
    "runID":8,
    "klimaat":"zeer extreem",
    "zichtjaar":2100,
    "afvoerverdeling":2018,
    "afvoerbeperking":false,
    "kwa":false,
    "zss":2.0,
    "discharge":"BP18STOOM2085",
    "demand":"BP18STOOM2085",
    "demand_corrected":"BP18STOOM2085_slr2"
  },
  {
    "runID":9,
    "klimaat":"zeer extreem",
    "zichtjaar":2150,
    "afvoerverdeling":2018,
    "afvoerbeperking":false,
    "kwa":false,
    "zss":3.5,
    "discharge":"BP18STOOM2085",
    "demand":"BP18STOOM2085",
    "demand_corrected":"BP18STOOM2085_slr3.5"
  },
  {
    "runID":10,
    "klimaat":"zeer extreem",
    "zichtjaar":2200,
    "afvoerverdeling":2018,
    "afvoerbeperking":false,
    "kwa":false,
    "zss":5.4,
    "discharge":"BP18STOOM2085",
    "demand":"BP18STOOM2085",
    "demand_corrected":"BP18STOOM2085_slr5.4"
  },
  {
    "runID":11,
    "klimaat":"laag",
    "zichtjaar":2023,
    "afvoerverdeling":1980,
    "afvoerbeperking":false,
    "kwa":false,
    "zss":0.0,
    "discharge":"BP18REF2017",
    "demand":"BP18REF2017",
    "demand_corrected":"BP18REF2017_slr0"
  },
  {
    "runID":12,
    "klimaat":"laag",
    "zichtjaar":2050,
    "afvoerverdeling":1980,
    "afvoerbeperking":false,
    "kwa":false,
    "zss":0.3,
    "discharge":"BP18REF2017",
    "demand":"BP18REF2017",
    "demand_corrected":"BP18REF2017_slr0.3"
  },
  {
    "runID":13,
    "klimaat":"laag",
    "zichtjaar":2100,
    "afvoerverdeling":1980,
    "afvoerbeperking":false,
    "kwa":false,
    "zss":0.5,
    "discharge":"BP18REF2017",
    "demand":"BP18REF2017",
    "demand_corrected":"BP18REF2017_slr0.5"
  },
  {
    "runID":14,
    "klimaat":"laag",
    "zichtjaar":2150,
    "afvoerverdeling":1980,
    "afvoerbeperking":false,
    "kwa":false,
    "zss":0.75,
    "discharge":"BP18REF2017",
    "demand":"BP18REF2017",
    "demand_corrected":"BP18REF2017_slr0.75"
  },
  {
    "runID":15,
    "klimaat":"laag",
    "zichtjaar":2200,
    "afvoerverdeling":1980,
    "afvoerbeperking":false,
    "kwa":false,
    "zss":1.0,
    "discharge":"BP18REF2017",
    "demand":"BP18REF2017",
    "demand_corrected":"BP18REF2017_slr1"
  },
  {
    "runID":16,
    "klimaat":"zeer extreem",
    "zichtjaar":2023,
    "afvoerverdeling":1980,
    "afvoerbeperking":false,
    "kwa":false,
    "zss":0.0,
    "discharge":"BP18REF2017",
    "demand":"BP18REF2017",
    "demand_corrected":"BP18REF2017_slr0"
  },
  {
    "runID":17,
    "klimaat":"zeer extreem",
    "zichtjaar":2050,
    "afvoerverdeling":1980,
    "afvoerbeperking":false,
    "kwa":false,
    "zss":0.5,
    "discharge":"BP18STOOM2050",
    "demand":"BP18STOOM2050",
    "demand_corrected":"BP18STOOM2050_slr0.5"
  },
  {
    "runID":18,
    "klimaat":"zeer extreem",
    "zichtjaar":2100,
    "afvoerverdeling":1980,
    "afvoerbeperking":false,
    "kwa":false,
    "zss":2.0,
    "discharge":"BP18STOOM2085",
    "demand":"BP18STOOM2085",
    "demand_corrected":"BP18STOOM2085_slr2"
  },
  {
    "runID":19,
    "klimaat":"zeer extreem",
    "zichtjaar":2150,
    "afvoerverdeling":1980,
    "afvoerbeperking":false,
    "kwa":false,
    "zss":3.5,
    "discharge":"BP18STOOM2085",
    "demand":"BP18STOOM2085",
    "demand_corrected":"BP18STOOM2085_slr3.5"
  },
  {
    "runID":20,
    "klimaat":"zeer extreem",
    "zichtjaar":2200,
    "afvoerverdeling":1980,
    "afvoerbeperking":false,
    "kwa":false,
    "zss":5.4,
    "discharge":"BP18STOOM2085",
    "demand":"BP18STOOM2085",
    "demand_corrected":"BP18STOOM2085_slr5.4"
  },
  {
    "runID":21,
    "klimaat":"laag",
    "zichtjaar":2023,
    "afvoerverdeling":2050,
    "afvoerbeperking":false,
    "kwa":false,
    "zss":0.0,
    "discharge":"BP18REF2017",
    "demand":"BP18REF2017",
    "demand_corrected":"BP18REF2017_slr0"
  },
  {
    "runID":22,
    "klimaat":"laag",
    "zichtjaar":2050,
    "afvoerverdeling":2050,
    "afvoerbeperking":false,
    "kwa":false,
    "zss":0.3,
    "discharge":"BP18REF2017",
    "demand":"BP18REF2017",
    "demand_corrected":"BP18REF2017_slr0.3"
  },
  {
    "runID":23,
    "klimaat":"laag",
    "zichtjaar":2100,
    "afvoerverdeling":2050,
    "afvoerbeperking":false,
    "kwa":false,
    "zss":0.5,
    "discharge":"BP18REF2017",
    "demand":"BP18REF2017",
    "demand_corrected":"BP18REF2017_slr0.5"
  },
  {
    "runID":24,
    "klimaat":"laag",
    "zichtjaar":2150,
    "afvoerverdeling":2050,
    "afvoerbeperking":false,
    "kwa":false,
    "zss":0.75,
    "discharge":"BP18REF2017",
    "demand":"BP18REF2017",
    "demand_corrected":"BP18REF2017_slr0.75"
  },
  {
    "runID":25,
    "klimaat":"laag",
    "zichtjaar":2200,
    "afvoerverdeling":2050,
    "afvoerbeperking":false,
    "kwa":false,
    "zss":1.0,
    "discharge":"BP18REF2017",
    "demand":"BP18REF2017",
    "demand_corrected":"BP18REF2017_slr1"
  },
  {
    "runID":26,
    "klimaat":"zeer extreem",
    "zichtjaar":2023,
    "afvoerverdeling":2050,
    "afvoerbeperking":false,
    "kwa":false,
    "zss":0.0,
    "discharge":"BP18REF2017",
    "demand":"BP18REF2017",
    "demand_corrected":"BP18REF2017_slr0"
  },
  {
    "runID":27,
    "klimaat":"zeer extreem",
    "zichtjaar":2050,
    "afvoerverdeling":2050,
    "afvoerbeperking":false,
    "kwa":false,
    "zss":0.5,
    "discharge":"BP18STOOM2050",
    "demand":"BP18STOOM2050",
    "demand_corrected":"BP18STOOM2050_slr0.5"
  },
  {
    "runID":28,
    "klimaat":"zeer extreem",
    "zichtjaar":2100,
    "afvoerverdeling":2050,
    "afvoerbeperking":false,
    "kwa":false,
    "zss":2.0,
    "discharge":"BP18STOOM2085",
    "demand":"BP18STOOM2085",
    "demand_corrected":"BP18STOOM2085_slr2"
  },
  {
    "runID":29,
    "klimaat":"zeer extreem",
    "zichtjaar":2150,
    "afvoerverdeling":2050,
    "afvoerbeperking":false,
    "kwa":false,
    "zss":3.5,
    "discharge":"BP18STOOM2085",
    "demand":"BP18STOOM2085",
    "demand_corrected":"BP18STOOM2085_slr3.5"
  },
  {
    "runID":30,
    "klimaat":"zeer extreem",
    "zichtjaar":2200,
    "afvoerverdeling":2050,
    "afvoerbeperking":false,
    "kwa":false,
    "zss":5.4,
    "discharge":"BP18STOOM2085",
    "demand":"BP18STOOM2085",
    "demand_corrected":"BP18STOOM2085_slr5.4"
  },
  {
    "runID":31,
    "klimaat":"laag",
    "zichtjaar":2023,
    "afvoerverdeling":2018,
    "afvoerbeperking":true,
    "kwa":false,
    "zss":0.0,
    "discharge":"BP18REF2017",
    "demand":"BP18REF2017",
    "demand_corrected":"BP18REF2017_slr0"
  },
  {
    "runID":32,
    "klimaat":"laag",
    "zichtjaar":2050,
    "afvoerverdeling":2018,
    "afvoerbeperking":true,
    "kwa":false,
    "zss":0.3,
    "discharge":"BP18REF2017",
    "demand":"BP18REF2017",
    "demand_corrected":"BP18REF2017_slr0.3"
  },
  {
    "runID":33,
    "klimaat":"laag",
    "zichtjaar":2100,
    "afvoerverdeling":2018,
    "afvoerbeperking":true,
    "kwa":false,
    "zss":0.5,
    "discharge":"BP18REF2017",
    "demand":"BP18REF2017",
    "demand_corrected":"BP18REF2017_slr0.5"
  },
  {
    "runID":34,
    "klimaat":"laag",
    "zichtjaar":2150,
    "afvoerverdeling":2018,
    "afvoerbeperking":true,
    "kwa":false,
    "zss":0.75,
    "discharge":"BP18REF2017",
    "demand":"BP18REF2017",
    "demand_corrected":"BP18REF2017_slr0.75"
  },
  {
    "runID":35,
    "klimaat":"laag",
    "zichtjaar":2200,
    "afvoerverdeling":2018,
    "afvoerbeperking":true,
    "kwa":false,
    "zss":1.0,
    "discharge":"BP18REF2017",
    "demand":"BP18REF2017",
    "demand_corrected":"BP18REF2017_slr1"
  },
  {
    "runID":36,
    "klimaat":"zeer extreem",
    "zichtjaar":2023,
    "afvoerverdeling":2018,
    "afvoerbeperking":true,
    "kwa":false,
    "zss":0.0,
    "discharge":"BP18REF2017",
    "demand":"BP18REF2017",
    "demand_corrected":"BP18REF2017_slr0"
  },
  {
    "runID":37,
    "klimaat":"zeer extreem",
    "zichtjaar":2050,
    "afvoerverdeling":2018,
    "afvoerbeperking":true,
    "kwa":false,
    "zss":0.5,
    "discharge":"BP18STOOM2050",
    "demand":"BP18STOOM2050",
    "demand_corrected":"BP18STOOM2050_slr0.5"
  },
  {
    "runID":38,
    "klimaat":"zeer extreem",
    "zichtjaar":2100,
    "afvoerverdeling":2018,
    "afvoerbeperking":true,
    "kwa":false,
    "zss":2.0,
    "discharge":"BP18STOOM2085",
    "demand":"BP18STOOM2085",
    "demand_corrected":"BP18STOOM2085_slr2"
  },
  {
    "runID":39,
    "klimaat":"zeer extreem",
    "zichtjaar":2150,
    "afvoerverdeling":2018,
    "afvoerbeperking":true,
    "kwa":false,
    "zss":3.5,
    "discharge":"BP18STOOM2085",
    "demand":"BP18STOOM2085",
    "demand_corrected":"BP18STOOM2085_slr3.5"
  },
  {
    "runID":40,
    "klimaat":"zeer extreem",
    "zichtjaar":2200,
    "afvoerverdeling":2018,
    "afvoerbeperking":true,
    "kwa":false,
    "zss":5.4,
    "discharge":"BP18STOOM2085",
    "demand":"BP18STOOM2085",
    "demand_corrected":"BP18STOOM2085_slr5.4"
  },
  {
    "runID":41,
    "klimaat":"laag",
    "zichtjaar":2023,
    "afvoerverdeling":1980,
    "afvoerbeperking":true,
    "kwa":false,
    "zss":0.0,
    "discharge":"BP18REF2017",
    "demand":"BP18REF2017",
    "demand_corrected":"BP18REF2017_slr0"
  },
  {
    "runID":42,
    "klimaat":"laag",
    "zichtjaar":2050,
    "afvoerverdeling":1980,
    "afvoerbeperking":true,
    "kwa":false,
    "zss":0.3,
    "discharge":"BP18REF2017",
    "demand":"BP18REF2017",
    "demand_corrected":"BP18REF2017_slr0.3"
  },
  {
    "runID":43,
    "klimaat":"laag",
    "zichtjaar":2100,
    "afvoerverdeling":1980,
    "afvoerbeperking":true,
    "kwa":false,
    "zss":0.5,
    "discharge":"BP18REF2017",
    "demand":"BP18REF2017",
    "demand_corrected":"BP18REF2017_slr0.5"
  },
  {
    "runID":44,
    "klimaat":"laag",
    "zichtjaar":2150,
    "afvoerverdeling":1980,
    "afvoerbeperking":true,
    "kwa":false,
    "zss":0.75,
    "discharge":"BP18REF2017",
    "demand":"BP18REF2017",
    "demand_corrected":"BP18REF2017_slr0.75"
  },
  {
    "runID":45,
    "klimaat":"laag",
    "zichtjaar":2200,
    "afvoerverdeling":1980,
    "afvoerbeperking":true,
    "kwa":false,
    "zss":1.0,
    "discharge":"BP18REF2017",
    "demand":"BP18REF2017",
    "demand_corrected":"BP18REF2017_slr1"
  },
  {
    "runID":46,
    "klimaat":"zeer extreem",
    "zichtjaar":2023,
    "afvoerverdeling":1980,
    "afvoerbeperking":true,
    "kwa":false,
    "zss":0.0,
    "discharge":"BP18REF2017",
    "demand":"BP18REF2017",
    "demand_corrected":"BP18REF2017_slr0"
  },
  {
    "runID":47,
    "klimaat":"zeer extreem",
    "zichtjaar":2050,
    "afvoerverdeling":1980,
    "afvoerbeperking":true,
    "kwa":false,
    "zss":0.5,
    "discharge":"BP18STOOM2050",
    "demand":"BP18STOOM2050",
    "demand_corrected":"BP18STOOM2050_slr0.5"
  },
  {
    "runID":48,
    "klimaat":"zeer extreem",
    "zichtjaar":2100,
    "afvoerverdeling":1980,
    "afvoerbeperking":true,
    "kwa":false,
    "zss":2.0,
    "discharge":"BP18STOOM2085",
    "demand":"BP18STOOM2085",
    "demand_corrected":"BP18STOOM2085_slr2"
  },
  {
    "runID":49,
    "klimaat":"zeer extreem",
    "zichtjaar":2150,
    "afvoerverdeling":1980,
    "afvoerbeperking":true,
    "kwa":false,
    "zss":3.5,
    "discharge":"BP18STOOM2085",
    "demand":"BP18STOOM2085",
    "demand_corrected":"BP18STOOM2085_slr3.5"
  },
  {
    "runID":50,
    "klimaat":"zeer extreem",
    "zichtjaar":2200,
    "afvoerverdeling":1980,
    "afvoerbeperking":true,
    "kwa":false,
    "zss":5.4,
    "discharge":"BP18STOOM2085",
    "demand":"BP18STOOM2085",
    "demand_corrected":"BP18STOOM2085_slr5.4"
  },
  {
    "runID":51,
    "klimaat":"laag",
    "zichtjaar":2023,
    "afvoerverdeling":2050,
    "afvoerbeperking":true,
    "kwa":false,
    "zss":0.0,
    "discharge":"BP18REF2017",
    "demand":"BP18REF2017",
    "demand_corrected":"BP18REF2017_slr0"
  },
  {
    "runID":52,
    "klimaat":"laag",
    "zichtjaar":2050,
    "afvoerverdeling":2050,
    "afvoerbeperking":true,
    "kwa":false,
    "zss":0.3,
    "discharge":"BP18REF2017",
    "demand":"BP18REF2017",
    "demand_corrected":"BP18REF2017_slr0.3"
  },
  {
    "runID":53,
    "klimaat":"laag",
    "zichtjaar":2100,
    "afvoerverdeling":2050,
    "afvoerbeperking":true,
    "kwa":false,
    "zss":0.5,
    "discharge":"BP18REF2017",
    "demand":"BP18REF2017",
    "demand_corrected":"BP18REF2017_slr0.5"
  },
  {
    "runID":54,
    "klimaat":"laag",
    "zichtjaar":2150,
    "afvoerverdeling":2050,
    "afvoerbeperking":true,
    "kwa":false,
    "zss":0.75,
    "discharge":"BP18REF2017",
    "demand":"BP18REF2017",
    "demand_corrected":"BP18REF2017_slr0.75"
  },
  {
    "runID":55,
    "klimaat":"laag",
    "zichtjaar":2200,
    "afvoerverdeling":2050,
    "afvoerbeperking":true,
    "kwa":false,
    "zss":1.0,
    "discharge":"BP18REF2017",
    "demand":"BP18REF2017",
    "demand_corrected":"BP18REF2017_slr1"
  },
  {
    "runID":56,
    "klimaat":"zeer extreem",
    "zichtjaar":2023,
    "afvoerverdeling":2050,
    "afvoerbeperking":true,
    "kwa":false,
    "zss":0.0,
    "discharge":"BP18REF2017",
    "demand":"BP18REF2017",
    "demand_corrected":"BP18REF2017_slr0"
  },
  {
    "runID":57,
    "klimaat":"zeer extreem",
    "zichtjaar":2050,
    "afvoerverdeling":2050,
    "afvoerbeperking":true,
    "kwa":false,
    "zss":0.5,
    "discharge":"BP18STOOM2050",
    "demand":"BP18STOOM2050",
    "demand_corrected":"BP18STOOM2050_slr0.5"
  },
  {
    "runID":58,
    "klimaat":"zeer extreem",
    "zichtjaar":2100,
    "afvoerverdeling":2050,
    "afvoerbeperking":true,
    "kwa":false,
    "zss":2.0,
    "discharge":"BP18STOOM2085",
    "demand":"BP18STOOM2085",
    "demand_corrected":"BP18STOOM2085_slr2"
  },
  {
    "runID":59,
    "klimaat":"zeer extreem",
    "zichtjaar":2150,
    "afvoerverdeling":2050,
    "afvoerbeperking":true,
    "kwa":false,
    "zss":3.5,
    "discharge":"BP18STOOM2085",
    "demand":"BP18STOOM2085",
    "demand_corrected":"BP18STOOM2085_slr3.5"
  },
  {
    "runID":60,
    "klimaat":"zeer extreem",
    "zichtjaar":2200,
    "afvoerverdeling":2050,
    "afvoerbeperking":true,
    "kwa":false,
    "zss":5.4,
    "discharge":"BP18STOOM2085",
    "demand":"BP18STOOM2085",
    "demand_corrected":"BP18STOOM2085_slr5.4"
  },
  {
    "runID":61,
    "klimaat":"laag",
    "zichtjaar":2023,
    "afvoerverdeling":2018,
    "afvoerbeperking":false,
    "kwa":true,
    "zss":0.0,
    "discharge":"BP18REF2017",
    "demand":"BP18REF2017",
    "demand_corrected":"BP18REF2017_slr0"
  },
  {
    "runID":62,
    "klimaat":"laag",
    "zichtjaar":2050,
    "afvoerverdeling":2018,
    "afvoerbeperking":false,
    "kwa":true,
    "zss":0.3,
    "discharge":"BP18REF2017",
    "demand":"BP18REF2017",
    "demand_corrected":"BP18REF2017_slr0.3"
  },
  {
    "runID":63,
    "klimaat":"laag",
    "zichtjaar":2100,
    "afvoerverdeling":2018,
    "afvoerbeperking":false,
    "kwa":true,
    "zss":0.5,
    "discharge":"BP18REF2017",
    "demand":"BP18REF2017",
    "demand_corrected":"BP18REF2017_slr0.5"
  },
  {
    "runID":64,
    "klimaat":"laag",
    "zichtjaar":2150,
    "afvoerverdeling":2018,
    "afvoerbeperking":false,
    "kwa":true,
    "zss":0.75,
    "discharge":"BP18REF2017",
    "demand":"BP18REF2017",
    "demand_corrected":"BP18REF2017_slr0.75"
  },
  {
    "runID":65,
    "klimaat":"laag",
    "zichtjaar":2200,
    "afvoerverdeling":2018,
    "afvoerbeperking":false,
    "kwa":true,
    "zss":1.0,
    "discharge":"BP18REF2017",
    "demand":"BP18REF2017",
    "demand_corrected":"BP18REF2017_slr1"
  },
  {
    "runID":66,
    "klimaat":"zeer extreem",
    "zichtjaar":2023,
    "afvoerverdeling":2018,
    "afvoerbeperking":false,
    "kwa":true,
    "zss":0.0,
    "discharge":"BP18REF2017",
    "demand":"BP18REF2017",
    "demand_corrected":"BP18REF2017_slr0"
  },
  {
    "runID":67,
    "klimaat":"zeer extreem",
    "zichtjaar":2050,
    "afvoerverdeling":2018,
    "afvoerbeperking":false,
    "kwa":true,
    "zss":0.5,
    "discharge":"BP18STOOM2050",
    "demand":"BP18STOOM2050",
    "demand_corrected":"BP18STOOM2050_slr0.5"
  },
  {
    "runID":68,
    "klimaat":"zeer extreem",
    "zichtjaar":2100,
    "afvoerverdeling":2018,
    "afvoerbeperking":false,
    "kwa":true,
    "zss":2.0,
    "discharge":"BP18STOOM2085",
    "demand":"BP18STOOM2085",
    "demand_corrected":"BP18STOOM2085_slr2"
  },
  {
    "runID":69,
    "klimaat":"zeer extreem",
    "zichtjaar":2150,
    "afvoerverdeling":2018,
    "afvoerbeperking":false,
    "kwa":true,
    "zss":3.5,
    "discharge":"BP18STOOM2085",
    "demand":"BP18STOOM2085",
    "demand_corrected":"BP18STOOM2085_slr3.5"
  },
  {
    "runID":70,
    "klimaat":"zeer extreem",
    "zichtjaar":2200,
    "afvoerverdeling":2018,
    "afvoerbeperking":false,
    "kwa":true,
    "zss":5.4,
    "discharge":"BP18STOOM2085",
    "demand":"BP18STOOM2085",
    "demand_corrected":"BP18STOOM2085_slr5.4"
  },
  {
    "runID":71,
    "klimaat":"laag",
    "zichtjaar":2023,
    "afvoerverdeling":1980,
    "afvoerbeperking":false,
    "kwa":true,
    "zss":0.0,
    "discharge":"BP18REF2017",
    "demand":"BP18REF2017",
    "demand_corrected":"BP18REF2017_slr0"
  },
  {
    "runID":72,
    "klimaat":"laag",
    "zichtjaar":2050,
    "afvoerverdeling":1980,
    "afvoerbeperking":false,
    "kwa":true,
    "zss":0.3,
    "discharge":"BP18REF2017",
    "demand":"BP18REF2017",
    "demand_corrected":"BP18REF2017_slr0.3"
  },
  {
    "runID":73,
    "klimaat":"laag",
    "zichtjaar":2100,
    "afvoerverdeling":1980,
    "afvoerbeperking":false,
    "kwa":true,
    "zss":0.5,
    "discharge":"BP18REF2017",
    "demand":"BP18REF2017",
    "demand_corrected":"BP18REF2017_slr0.5"
  },
  {
    "runID":74,
    "klimaat":"laag",
    "zichtjaar":2150,
    "afvoerverdeling":1980,
    "afvoerbeperking":false,
    "kwa":true,
    "zss":0.75,
    "discharge":"BP18REF2017",
    "demand":"BP18REF2017",
    "demand_corrected":"BP18REF2017_slr0.75"
  },
  {
    "runID":75,
    "klimaat":"laag",
    "zichtjaar":2200,
    "afvoerverdeling":1980,
    "afvoerbeperking":false,
    "kwa":true,
    "zss":1.0,
    "discharge":"BP18REF2017",
    "demand":"BP18REF2017",
    "demand_corrected":"BP18REF2017_slr1"
  },
  {
    "runID":76,
    "klimaat":"zeer extreem",
    "zichtjaar":2023,
    "afvoerverdeling":1980,
    "afvoerbeperking":false,
    "kwa":true,
    "zss":0.0,
    "discharge":"BP18REF2017",
    "demand":"BP18REF2017",
    "demand_corrected":"BP18REF2017_slr0"
  },
  {
    "runID":77,
    "klimaat":"zeer extreem",
    "zichtjaar":2050,
    "afvoerverdeling":1980,
    "afvoerbeperking":false,
    "kwa":true,
    "zss":0.5,
    "discharge":"BP18STOOM2050",
    "demand":"BP18STOOM2050",
    "demand_corrected":"BP18STOOM2050_slr0.5"
  },
  {
    "runID":78,
    "klimaat":"zeer extreem",
    "zichtjaar":2100,
    "afvoerverdeling":1980,
    "afvoerbeperking":false,
    "kwa":true,
    "zss":2.0,
    "discharge":"BP18STOOM2085",
    "demand":"BP18STOOM2085",
    "demand_corrected":"BP18STOOM2085_slr2"
  },
  {
    "runID":79,
    "klimaat":"zeer extreem",
    "zichtjaar":2150,
    "afvoerverdeling":1980,
    "afvoerbeperking":false,
    "kwa":true,
    "zss":3.5,
    "discharge":"BP18STOOM2085",
    "demand":"BP18STOOM2085",
    "demand_corrected":"BP18STOOM2085_slr3.5"
  },
  {
    "runID":80,
    "klimaat":"zeer extreem",
    "zichtjaar":2200,
    "afvoerverdeling":1980,
    "afvoerbeperking":false,
    "kwa":true,
    "zss":5.4,
    "discharge":"BP18STOOM2085",
    "demand":"BP18STOOM2085",
    "demand_corrected":"BP18STOOM2085_slr5.4"
  },
  {
    "runID":81,
    "klimaat":"laag",
    "zichtjaar":2023,
    "afvoerverdeling":2050,
    "afvoerbeperking":false,
    "kwa":true,
    "zss":0.0,
    "discharge":"BP18REF2017",
    "demand":"BP18REF2017",
    "demand_corrected":"BP18REF2017_slr0"
  },
  {
    "runID":82,
    "klimaat":"laag",
    "zichtjaar":2050,
    "afvoerverdeling":2050,
    "afvoerbeperking":false,
    "kwa":true,
    "zss":0.3,
    "discharge":"BP18REF2017",
    "demand":"BP18REF2017",
    "demand_corrected":"BP18REF2017_slr0.3"
  },
  {
    "runID":83,
    "klimaat":"laag",
    "zichtjaar":2100,
    "afvoerverdeling":2050,
    "afvoerbeperking":false,
    "kwa":true,
    "zss":0.5,
    "discharge":"BP18REF2017",
    "demand":"BP18REF2017",
    "demand_corrected":"BP18REF2017_slr0.5"
  },
  {
    "runID":84,
    "klimaat":"laag",
    "zichtjaar":2150,
    "afvoerverdeling":2050,
    "afvoerbeperking":false,
    "kwa":true,
    "zss":0.75,
    "discharge":"BP18REF2017",
    "demand":"BP18REF2017",
    "demand_corrected":"BP18REF2017_slr0.75"
  },
  {
    "runID":85,
    "klimaat":"laag",
    "zichtjaar":2200,
    "afvoerverdeling":2050,
    "afvoerbeperking":false,
    "kwa":true,
    "zss":1.0,
    "discharge":"BP18REF2017",
    "demand":"BP18REF2017",
    "demand_corrected":"BP18REF2017_slr1"
  },
  {
    "runID":86,
    "klimaat":"zeer extreem",
    "zichtjaar":2023,
    "afvoerverdeling":2050,
    "afvoerbeperking":false,
    "kwa":true,
    "zss":0.0,
    "discharge":"BP18REF2017",
    "demand":"BP18REF2017",
    "demand_corrected":"BP18REF2017_slr0"
  },
  {
    "runID":87,
    "klimaat":"zeer extreem",
    "zichtjaar":2050,
    "afvoerverdeling":2050,
    "afvoerbeperking":false,
    "kwa":true,
    "zss":0.5,
    "discharge":"BP18STOOM2050",
    "demand":"BP18STOOM2050",
    "demand_corrected":"BP18STOOM2050_slr0.5"
  },
  {
    "runID":88,
    "klimaat":"zeer extreem",
    "zichtjaar":2100,
    "afvoerverdeling":2050,
    "afvoerbeperking":false,
    "kwa":true,
    "zss":2.0,
    "discharge":"BP18STOOM2085",
    "demand":"BP18STOOM2085",
    "demand_corrected":"BP18STOOM2085_slr2"
  },
  {
    "runID":89,
    "klimaat":"zeer extreem",
    "zichtjaar":2150,
    "afvoerverdeling":2050,
    "afvoerbeperking":false,
    "kwa":true,
    "zss":3.5,
    "discharge":"BP18STOOM2085",
    "demand":"BP18STOOM2085",
    "demand_corrected":"BP18STOOM2085_slr3.5"
  },
  {
    "runID":90,
    "klimaat":"zeer extreem",
    "zichtjaar":2200,
    "afvoerverdeling":2050,
    "afvoerbeperking":false,
    "kwa":true,
    "zss":5.4,
    "discharge":"BP18STOOM2085",
    "demand":"BP18STOOM2085",
    "demand_corrected":"BP18STOOM2085_slr5.4"
  },
  {
    "runID":91,
    "klimaat":"laag",
    "zichtjaar":2023,
    "afvoerverdeling":2018,
    "afvoerbeperking":true,
    "kwa":true,
    "zss":0.0,
    "discharge":"BP18REF2017",
    "demand":"BP18REF2017",
    "demand_corrected":"BP18REF2017_slr0"
  },
  {
    "runID":92,
    "klimaat":"laag",
    "zichtjaar":2050,
    "afvoerverdeling":2018,
    "afvoerbeperking":true,
    "kwa":true,
    "zss":0.3,
    "discharge":"BP18REF2017",
    "demand":"BP18REF2017",
    "demand_corrected":"BP18REF2017_slr0.3"
  },
  {
    "runID":93,
    "klimaat":"laag",
    "zichtjaar":2100,
    "afvoerverdeling":2018,
    "afvoerbeperking":true,
    "kwa":true,
    "zss":0.5,
    "discharge":"BP18REF2017",
    "demand":"BP18REF2017",
    "demand_corrected":"BP18REF2017_slr0.5"
  },
  {
    "runID":94,
    "klimaat":"laag",
    "zichtjaar":2150,
    "afvoerverdeling":2018,
    "afvoerbeperking":true,
    "kwa":true,
    "zss":0.75,
    "discharge":"BP18REF2017",
    "demand":"BP18REF2017",
    "demand_corrected":"BP18REF2017_slr0.75"
  },
  {
    "runID":95,
    "klimaat":"laag",
    "zichtjaar":2200,
    "afvoerverdeling":2018,
    "afvoerbeperking":true,
    "kwa":true,
    "zss":1.0,
    "discharge":"BP18REF2017",
    "demand":"BP18REF2017",
    "demand_corrected":"BP18REF2017_slr1"
  },
  {
    "runID":96,
    "klimaat":"zeer extreem",
    "zichtjaar":2023,
    "afvoerverdeling":2018,
    "afvoerbeperking":true,
    "kwa":true,
    "zss":0.0,
    "discharge":"BP18REF2017",
    "demand":"BP18REF2017",
    "demand_corrected":"BP18REF2017_slr0"
  },
  {
    "runID":97,
    "klimaat":"zeer extreem",
    "zichtjaar":2050,
    "afvoerverdeling":2018,
    "afvoerbeperking":true,
    "kwa":true,
    "zss":0.5,
    "discharge":"BP18STOOM2050",
    "demand":"BP18STOOM2050",
    "demand_corrected":"BP18STOOM2050_slr0.5"
  },
  {
    "runID":98,
    "klimaat":"zeer extreem",
    "zichtjaar":2100,
    "afvoerverdeling":2018,
    "afvoerbeperking":true,
    "kwa":true,
    "zss":2.0,
    "discharge":"BP18STOOM2085",
    "demand":"BP18STOOM2085",
    "demand_corrected":"BP18STOOM2085_slr2"
  },
  {
    "runID":99,
    "klimaat":"zeer extreem",
    "zichtjaar":2150,
    "afvoerverdeling":2018,
    "afvoerbeperking":true,
    "kwa":true,
    "zss":3.5,
    "discharge":"BP18STOOM2085",
    "demand":"BP18STOOM2085",
    "demand_corrected":"BP18STOOM2085_slr3.5"
  },
  {
    "runID":100,
    "klimaat":"zeer extreem",
    "zichtjaar":2200,
    "afvoerverdeling":2018,
    "afvoerbeperking":true,
    "kwa":true,
    "zss":5.4,
    "discharge":"BP18STOOM2085",
    "demand":"BP18STOOM2085",
    "demand_corrected":"BP18STOOM2085_slr5.4"
  },
  {
    "runID":101,
    "klimaat":"laag",
    "zichtjaar":2023,
    "afvoerverdeling":1980,
    "afvoerbeperking":true,
    "kwa":true,
    "zss":0.0,
    "discharge":"BP18REF2017",
    "demand":"BP18REF2017",
    "demand_corrected":"BP18REF2017_slr0"
  },
  {
    "runID":102,
    "klimaat":"laag",
    "zichtjaar":2050,
    "afvoerverdeling":1980,
    "afvoerbeperking":true,
    "kwa":true,
    "zss":0.3,
    "discharge":"BP18REF2017",
    "demand":"BP18REF2017",
    "demand_corrected":"BP18REF2017_slr0.3"
  },
  {
    "runID":103,
    "klimaat":"laag",
    "zichtjaar":2100,
    "afvoerverdeling":1980,
    "afvoerbeperking":true,
    "kwa":true,
    "zss":0.5,
    "discharge":"BP18REF2017",
    "demand":"BP18REF2017",
    "demand_corrected":"BP18REF2017_slr0.5"
  },
  {
    "runID":104,
    "klimaat":"laag",
    "zichtjaar":2150,
    "afvoerverdeling":1980,
    "afvoerbeperking":true,
    "kwa":true,
    "zss":0.75,
    "discharge":"BP18REF2017",
    "demand":"BP18REF2017",
    "demand_corrected":"BP18REF2017_slr0.75"
  },
  {
    "runID":105,
    "klimaat":"laag",
    "zichtjaar":2200,
    "afvoerverdeling":1980,
    "afvoerbeperking":true,
    "kwa":true,
    "zss":1.0,
    "discharge":"BP18REF2017",
    "demand":"BP18REF2017",
    "demand_corrected":"BP18REF2017_slr1"
  },
  {
    "runID":106,
    "klimaat":"zeer extreem",
    "zichtjaar":2023,
    "afvoerverdeling":1980,
    "afvoerbeperking":true,
    "kwa":true,
    "zss":0.0,
    "discharge":"BP18REF2017",
    "demand":"BP18REF2017",
    "demand_corrected":"BP18REF2017_slr0"
  },
  {
    "runID":107,
    "klimaat":"zeer extreem",
    "zichtjaar":2050,
    "afvoerverdeling":1980,
    "afvoerbeperking":true,
    "kwa":true,
    "zss":0.5,
    "discharge":"BP18STOOM2050",
    "demand":"BP18STOOM2050",
    "demand_corrected":"BP18STOOM2050_slr0.5"
  },
  {
    "runID":108,
    "klimaat":"zeer extreem",
    "zichtjaar":2100,
    "afvoerverdeling":1980,
    "afvoerbeperking":true,
    "kwa":true,
    "zss":2.0,
    "discharge":"BP18STOOM2085",
    "demand":"BP18STOOM2085",
    "demand_corrected":"BP18STOOM2085_slr2"
  },
  {
    "runID":109,
    "klimaat":"zeer extreem",
    "zichtjaar":2150,
    "afvoerverdeling":1980,
    "afvoerbeperking":true,
    "kwa":true,
    "zss":3.5,
    "discharge":"BP18STOOM2085",
    "demand":"BP18STOOM2085",
    "demand_corrected":"BP18STOOM2085_slr3.5"
  },
  {
    "runID":110,
    "klimaat":"zeer extreem",
    "zichtjaar":2200,
    "afvoerverdeling":1980,
    "afvoerbeperking":true,
    "kwa":true,
    "zss":5.4,
    "discharge":"BP18STOOM2085",
    "demand":"BP18STOOM2085",
    "demand_corrected":"BP18STOOM2085_slr5.4"
  },
  {
    "runID":111,
    "klimaat":"laag",
    "zichtjaar":2023,
    "afvoerverdeling":2050,
    "afvoerbeperking":true,
    "kwa":true,
    "zss":0.0,
    "discharge":"BP18REF2017",
    "demand":"BP18REF2017",
    "demand_corrected":"BP18REF2017_slr0"
  },
  {
    "runID":112,
    "klimaat":"laag",
    "zichtjaar":2050,
    "afvoerverdeling":2050,
    "afvoerbeperking":true,
    "kwa":true,
    "zss":0.3,
    "discharge":"BP18REF2017",
    "demand":"BP18REF2017",
    "demand_corrected":"BP18REF2017_slr0.3"
  },
  {
    "runID":113,
    "klimaat":"laag",
    "zichtjaar":2100,
    "afvoerverdeling":2050,
    "afvoerbeperking":true,
    "kwa":true,
    "zss":0.5,
    "discharge":"BP18REF2017",
    "demand":"BP18REF2017",
    "demand_corrected":"BP18REF2017_slr0.5"
  },
  {
    "runID":114,
    "klimaat":"laag",
    "zichtjaar":2150,
    "afvoerverdeling":2050,
    "afvoerbeperking":true,
    "kwa":true,
    "zss":0.75,
    "discharge":"BP18REF2017",
    "demand":"BP18REF2017",
    "demand_corrected":"BP18REF2017_slr0.75"
  },
  {
    "runID":115,
    "klimaat":"laag",
    "zichtjaar":2200,
    "afvoerverdeling":2050,
    "afvoerbeperking":true,
    "kwa":true,
    "zss":1.0,
    "discharge":"BP18REF2017",
    "demand":"BP18REF2017",
    "demand_corrected":"BP18REF2017_slr1"
  },
  {
    "runID":116,
    "klimaat":"zeer extreem",
    "zichtjaar":2023,
    "afvoerverdeling":2050,
    "afvoerbeperking":true,
    "kwa":true,
    "zss":0.0,
    "discharge":"BP18REF2017",
    "demand":"BP18REF2017",
    "demand_corrected":"BP18REF2017_slr0"
  },
  {
    "runID":117,
    "klimaat":"zeer extreem",
    "zichtjaar":2050,
    "afvoerverdeling":2050,
    "afvoerbeperking":true,
    "kwa":true,
    "zss":0.5,
    "discharge":"BP18STOOM2050",
    "demand":"BP18STOOM2050",
    "demand_corrected":"BP18STOOM2050_slr0.5"
  },
  {
    "runID":118,
    "klimaat":"zeer extreem",
    "zichtjaar":2100,
    "afvoerverdeling":2050,
    "afvoerbeperking":true,
    "kwa":true,
    "zss":2.0,
    "discharge":"BP18STOOM2085",
    "demand":"BP18STOOM2085",
    "demand_corrected":"BP18STOOM2085_slr2"
  },
  {
    "runID":119,
    "klimaat":"zeer extreem",
    "zichtjaar":2150,
    "afvoerverdeling":2050,
    "afvoerbeperking":true,
    "kwa":true,
    "zss":3.5,
    "discharge":"BP18STOOM2085",
    "demand":"BP18STOOM2085",
    "demand_corrected":"BP18STOOM2085_slr3.5"
  },
  {
    "runID":120,
    "klimaat":"zeer extreem",
    "zichtjaar":2200,
    "afvoerverdeling":2050,
    "afvoerbeperking":true,
    "kwa":true,
    "zss":5.4,
    "discharge":"BP18STOOM2085",
    "demand":"BP18STOOM2085",
    "demand_corrected":"BP18STOOM2085_slr5.4"
  }
]